{
  "title": "수업료를 돌려주세요",
  "author": "프릿츠 카린시",
  "characters": [
    "교장",
    "물짱구",
    "물리선생",
    "지리선생",
    "역사선생",
    "수학선생",
    "사환"
  ],
  "scenes": [
    {
      "setting": "[무대]",
      "directions": [
        {
          "type": "direction",
          "content": "(중앙에 교장 책상 의자 좌우에 두 개씩 네 개의 의자 팻말이 교장 머리 위에는 전화기 한대와 몇 개의 결재서류 옆에는 우승기 비슷한 것이 놓여 있다.교장은 회전의자에 앉은 체 열심히 무엇인가 적고 있다.물주전자와 잔이 책상 위에 놓여있다.)"
        }
      ],
      "dialogues": [
        {
          "character": "교장",
          "line": "아 무슨 일이지?"
        },
        {
          "character": "사환",
          "line": "저 어떤 사람이 교장 선생님을 뵙자는 데요."
        },
        {
          "character": "교장",
          "pre_directions": "(몸을 지키며 위풍 있게)",
          "line": "난 면회 시간에만 학부형을 만난다는 걸 잊었나?나중에 오시라고 해."
        },
        {
          "character": "사환",
          "line": "예?예 저 그런데 그분은 학부형 같지가 않던데요?"
        },
        {
          "character": "교장",
          "line": "그럼 학생인가?"
        },
        {
          "character": "사환",
          "line": "그런 것 같지도 않던데요."
        },
        {
          "character": "교장",
          "line": "그럼 뭐란 말이야?학부형도 아니라면..."
        },
        {
          "character": "사환",
          "line": "수염이 낳던 뎁쇼."
        },
        {
          "character": "교장",
          "line": "수염?그래 영리해 보이던가 미련해 보이던가?"
        },
        {
          "character": "사환",
          "line": "제가 보기엔 꽤 똑똑하게 보였는데, 이름이 좀 …"
        },
        {
          "character": "교장",
          "line": "이름이?"
        },
        {
          "character": "사환",
          "line": "네!이름이 물짱구라구요!"
        },
        {
          "character": "교장",
          "line": "물짱구 ?"
        },
        {
          "character": "사환",
          "line": "네!"
        },
        {
          "character": "교장",
          "pre_directions": "(고개를 기웃 하더니)",
          "line": "좋아 가서 들어오라고 해.학교 사찰관은 아닌 모양이니까?"
        },
        {
          "character": "사환",
          "post_directions": "(나간다.잠시 후 물짱구 들어온다)",
          "line": "예!"
        },
        {
          "character": "물짱구",
          "line": "안녕하십니까?교장선생!"
        },
        {
          "character": "교장",
          "line": "어떻게 오셨습니까?"
        },
        {
          "character": "물짱구",
          "line": "난 물짱군데 날 잘 모르시겠습니까?"
        },
        {
          "character": "교장",
          "line": "글쎄 내가 보기에도 당신이 틀림없는 물짱구요.그런데 난 전혀 기억에 없는 짱군데요."
        },
        {
          "character": "물짱구",
          "line": "내가 변했을 지도 모르지.제기랄 당신의 학적부를 보면 내가 여기에 올 권리가 있다는 걸 아실 겁니다."
        },
        {
          "character": "교장",
          "line": "학적부요?"
        },
        {
          "character": "물짱구",
          "line": "교장 선생님.난 18년 전에 이 학교를 졸업한 학생입니다."
        },
        {
          "character": "교장",
          "line": "아 그럼 졸업증명서 때문에 오셨군요.그건 서무과에 가서 말씀하십시오."
        },
        {
          "character": "물짱구",
          "line": "그 놈에 졸업장은 여기에 가져 왔으니 두 번 다시 갈 필요는 없습니다.난 그것 때문에 여기 온건 아니니까요!"
        },
        {
          "character": "교장",
          "line": "그럼 뭐요?난 바쁜 사람이요.당신과 농담이나 하고 있을 시간이 없단 말이요."
        },
        {
          "character": "물짱구",
          "line": "교장 선생님.나도 쓸데없는 것으로 시간을 보낼 생각은 없소.난 18년 전에 내가 지불한 수험료를 돌려달라고 온 것입니다."
        },
        {
          "character": "교장",
          "line": "뭐 뭐라구요?"
        },
        {
          "character": "물짱구",
          "line": "뭐 내가 부자라면 까짓 돈 아무 것도 아니지만 난 지금 빈 털털이란 말이요?"
        },
        {
          "character": "교장",
          "line": "대체 무슨 말을 하고 있는 거요?"
        },
        {
          "character": "물짱구",
          "line": "수업료를 돌려 달란 말이에요.그래두 무슨 소린지 모르겠습니까?"
        },
        {
          "character": "교장",
          "line": "아니 어째서 수업료를 내 주어야 한단 말이요?"
        },
        {
          "character": "물짱구",
          "line": "왜냐하면 난 내가 낸 수업료의 대가를 하나도 못 받았거든요.이 졸업장은 내가 수업료를 내고 공부했다는 증명서인데, 이 놈의 학교에서 배운 여러 가지는 실제로는 하나도 사회생활에 적용되는 게 없단 말이에요.결국 난 쓸모 있는 것은 아무 것도 배운 게 없단 말입니다."
        },
        {
          "character": "교장",
          "line": "난 세상에 햇빛을 본 일에 당신 같은 괴짜는 처음 보우.무슨 그런 터무니없는 얘길 하시오."
        },
        {
          "character": "물짱구",
          "line": "터무니없다니요?이건 훌륭한 생각입니다.이런 좋은 생각은 도저히 내 머리론 할 수 없죠.이 학교의 교육은 날 무능한 바보로 만 들어 났으니까요.이 생각은 바로 30분전에 만난 꽁치란 친구가 내게 준 생각이죠."
        },
        {
          "character": "교장",
          "line": "그 꽁치란 사람두 당신 못지 않은 괴짜인 모양이군."
        },
        {
          "character": "물짱구",
          "line": "천만에요.그 친구는 훌륭합니다.난 수업료를 되찾으면 그 친구에게 좋은 선물 하나 선사할까 하는데요."
        },
        {
          "character": "교장",
          "line": "이러다간 나까지 미치고 말겠는데."
        },
        {
          "character": "물짱구",
          "line": "내가 해고를 당하고 한 푼도 없이 길을 가고 있는데 그 꽁치란 친구를 만났죠.그래서 \"여!어떻게 지내나?꽁치!\" 했더니 \"좋지!난 지금 내가 외국환에 투자했던 돈을 찾으러 가고 있는 길일세\" 하길래 \"외국환이란 무언가\" 하고 물었더니 \"미안하지만 그걸 설명할 시간이 없네.어쨌든 투자 한 돈이 새끼를 쳐서 꽤 큰 차액을 벌 수 있었단 말이야.또 보세.\" 그리고 가버렸단 말입니다.나라고 빈털터리가 되어서 거리를 어슬렁거리라는 법은 없지 않습니까?그렇게 된건 결국 엉터리 교육을 받았기 때문이지요.자!어서 수업료나 돌려 주세요."
        },
        {
          "character": "교장",
          "line": "농담은 집어 치워요!"
        },
        {
          "character": "물짱구",
          "line": "농담이라니요.난 아직 이렇게 심각해 본적은 없어요.만일 이 문제가 잘 해결이 안되면 난 직접 법원에 가서 고발하겠습니다."
        },
        {
          "character": "교장",
          "line": "법원?저 물짱난씨."
        },
        {
          "character": "물짱구",
          "line": "난 물짱구라니까요."
        },
        {
          "character": "교장",
          "line": "아 물짱구씨 실례했소.빌어먹을 이런 문제는 처음 당한 일인 만큼 조용히 생각해 봐야겠으니 며칠 후 다시 와 주시요."
        },
        {
          "character": "물짱구",
          "line": "안될 말씀이죠.그렇게 쉽게 날 내쫓을 수는 없을 겁니다.난 수업료를 되찾기 전엔 이 방문 밖을 나설 생각은 조금도 없으니까 알아서 하세요.교장 선생님도 내 생각이 틀렸다고 생각 안 할거예요.난 배운 게 없어서 일자리에 붙어 있을 수가 없으니까요.그건 시험을 치러 보면 당장 알 수 있죠.내가 얼마나 바보인지를 말입니다."
        },
        {
          "character": "교장",
          "line": "당신이 어떻게 얘기하든 좋소.그러나 이번 문제는 역사상 처음 있는 일인만큼 나 혼자 처리할 수 없는 일이요.미안 하지만 응접실에서 잠시 기다려 주시요.학과 주임들과 의논해야겠으니."
        },
        {
          "character": "물짱구",
          "line": "좋아요.그러나 빨리 해주세요.난 아주 급한 사람이니까요."
        },
        {
          "character": "교장",
          "line": "이봐!"
        },
        {
          "character": "사환",
          "line": "네!"
        },
        {
          "character": "교장",
          "line": "가서 학과 주임들을 급히 오라고 해.아주 특별한 회의라고."
        },
        {
          "character": "directions",
          "type": "direction",
          "content": "(교장은 방을 이리저리 돌아다닌다.잠시 뒤에 여러 선생들이 수근거리며 방으로 들어온다.선생들이 자리에 앉은 뒤에)"
        },
        {
          "character": "교장",
          "line": "얘 여러분 이건 좋지 않은 일이요.여러 선생님들.난 교장직 30년에 이런 일은 처음이요.빌어먹을 이게 무슨 망측스런 일이람!여러 선생님들!난 아주 특별한 사건 때문에 여러분을 모신 거요.자 앉으시오.회의를 시작합시다.얘 이건 다분히 환상적이고 믿을 수 없는 일이요.그건 이 학교를 18년 전에 졸업했다는 이름이 물----- 물----물-----?"
        },
        {
          "character": "지리",
          "line": "여기 있습니다."
        },
        {
          "character": "교장",
          "line": "이게 아니라--- 그 사람이--- 옳지!그렇지!물짱구!난 이런 일은 처음이요."
        },
        {
          "character": "역사",
          "line": "얘기를 해주세요."
        },
        {
          "character": "교장",
          "line": "그 친구는 수업료를 반환해 달라는 거요."
        },
        {
          "character": "일동",
          "line": "녜?"
        },
        {
          "character": "교장",
          "line": "그 이유는 직업을 잃은 데다 한푼도 없는 빈털터리가 되었다는 거죠.즉 아무 것도 배운 게 없다는 거죠."
        },
        {
          "character": "일동",
          "line": "예?"
        },
        {
          "character": "물리",
          "line": "여러분!이것은 별것이 아니라고 봅니다.에너지 불변 법칙에 의하면 어느 정해진 시간동안 선생이 학생의 머리 속에 지식을 넣어주면 일정한 시간동안 그 만큼 양을 잃게 되는 겁니다.그렇죠?역사 선생님!"
        },
        {
          "character": "역사",
          "line": "마---참.그러나 문명에 역사 속엔 마---참.그런 일이 없소.마---참 단지 부른 본가에서는 배우지도 듣지도 않았다고 하지만 마---참 그게 사실이라면---."
        },
        {
          "character": "물리",
          "line": "에너지 불변의 법칙은?"
        },
        {
          "character": "역사",
          "line": "문명의 역사 속에----"
        },
        {
          "character": "지리",
          "line": "어쨌든 그 친구는 지금 어디에 있죠?"
        },
        {
          "character": "교장",
          "line": "밖에서 기다리고 있소.그 친구는 자기가 아무 것도 배운 것이 없음을 시험으로 증명하겠다는 거요."
        },
        {
          "character": "수학",
          "line": "재시험이라---.여러분!우리가 그 물----물----"
        },
        {
          "character": "교장",
          "line": "짱구!"
        },
        {
          "character": "수학",
          "line": "짱구씨를 시험 친다고 해도 손해볼 것은 없다고 봅니다.그 물--- 물---"
        },
        {
          "character": "교장",
          "line": "짱구!"
        },
        {
          "character": "수학",
          "line": "감사합니다.그 물짱구는 날카로운 주둥이와 발톱으로 돈을 찾아가려는 겁니다.우리는 그런 자를 때려 부셔야 합니다."
        },
        {
          "character": "물리",
          "line": "어떻게 하죠"
        },
        {
          "character": "수학",
          "line": "합격 시켜야죠.아무 쉬운 문제로 말입니다.만일 그가 낙제하게 되면 제2 제3의 물짱구가 나타나게 될 거고 그렇게 되면 우리 교육계는 엉망진창이 되고, 국가의 흥망 성쇠는 말이 아닙니다.그러니까 그 친구의 해답이 어쨌든 간에 맞다고 선수를 쳐서 찬성해야 합니다.찬동합니까?"
        },
        {
          "character": "일동",
          "line": "찬성이요 (박수)"
        },
        {
          "character": "수학",
          "line": "그럼 시작합시다."
        },
        {
          "character": "교장",
          "line": "괜찮을까요 잘못돼서 신문에라도 난다면----"
        },
        {
          "character": "역사",
          "line": "어쨌든 해결 해야죠."
        },
        {
          "character": "교장",
          "line": "좋소 합시다, 이봐!"
        },
        {
          "character": "사환",
          "line": "네!"
        },
        {
          "character": "교장",
          "line": "그 물---물---물"
        },
        {
          "character": "수학",
          "line": "짱구!"
        },
        {
          "character": "교장",
          "line": "물짱구 씨를 들여보네."
        },
        {
          "character": "물짱구",
          "line": "자!안녕하십니까?이 엉터리 선생님들!"
        },
        {
          "character": "수학",
          "line": "흠.엉터리 선생님들 앉으십시다."
        },
        {
          "character": "역사",
          "line": "저 저런 고약한 놈"
        },
        {
          "character": "수학",
          "line": "당신이 지금 저희들에게 보여 주신 예법은 우리가 가르친 예의 법을 잘 기억하고 있음을 재치 있게 나타내셨습니다 그건 선생과 학생이 동등한 입장에서 서로 마음 놓고 의사를 표시하던 중세기 이후의 예절을 나타낸 겁니다.난 물짱구씨가 그 신사도에 관한 시험은 칠 필요가 없다고 주장하여 그 대신 최우수 학점을 드리겠습니다."
        },
        {
          "character": "일동",
          "line": "옳습니다!(박수)"
        },
        {
          "character": "교장",
          "line": "예절 최우수!"
        },
        {
          "character": "물짱구",
          "line": "아니?흠.내가 선수로 한대 맞은 셈이군.좋소, 당신네들이 그렇게 나온다면 나도 생각이 있소.그러나 그것 하나로 시험에 합격한 것은 아니요."
        },
        {
          "character": "교장",
          "line": "물론이죠 당신에 그 극히 바른 예의는 우리와는 아무 상관없으니까 (객석을 향해) 어차피 넌 돈 놈이니까 우린 시험치게 하고 점수 만 매기면 되는 거니까."
        },
        {
          "character": "물짱구",
          "line": "좋아요.좋아.자 어서 질문을 하시지 (객석을 향해) 이 당나귀들이 내 입에서 옳은 답이 하나라도 나오나 두고 봐라."
        },
        {
          "character": "교장",
          "line": "자!시험이요.처음 역사선생!"
        },
        {
          "character": "역사",
          "line": "물짱구씨 앉으시지 않겠소."
        },
        {
          "character": "물짱구",
          "line": "(객석을 향해) 앉으라고 이건 분명히 함정일거야.난 싫소.난 이렇게 똑바로 서 있겠소."
        },
        {
          "character": "지리",
          "line": "좋아요.물짱구씨는 앉기를 거부하므로 필기시험을 사절하겠다는 나타냄과 동시에 구두로 답하겠다는 것을 암시했습니다.이것은 그에 신체적 상태가 놀라운 것으로 그의 신체상태에 최우수를 주겠소.그리고 이것을 체육담당인 교장 선생님께 요구하는 바입니다."
        },
        {
          "character": "교장",
          "line": "신체 발육상태 최우수!"
        },
        {
          "character": "일동",
          "line": "이의 없음!"
        },
        {
          "character": "물짱구",
          "line": "어이쿠 내가 이런 날강도들한테 교육을 받았다니...좋다.두 번이나 당했지만 이번엔 안 될걸 정신 바짝 차린단 말이야."
        },
        {
          "character": "교장",
          "line": "주의력 최우수!"
        },
        {
          "character": "역사",
          "line": "인내력이 보통 아님!"
        },
        {
          "character": "수학",
          "line": "논리법 최우수!"
        },
        {
          "character": "물짱구",
          "line": "어서 진짜 질문이나 해!"
        },
        {
          "character": "지리",
          "line": "패가 무궁무진함!"
        },
        {
          "character": "물리",
          "line": "최우수!"
        },
        {
          "character": "물짱구",
          "line": "아이구 골치야!"
        },
        {
          "character": "교장",
          "line": "역사선생 어서 질문이나 하시요."
        },
        {
          "character": "역사",
          "line": "물론 하지요.애...잠깐만!"
        },
        {
          "character": "물짱구",
          "line": "어떻게 된 거요?이 바보 같은 역사선생 당신은 그래 그 하고 많은 시험문제를 하나도 모른단 말이요?"
        },
        {
          "character": "역사",
          "line": "아!수험생이 질문에 답하시오.어느 나라에서 30년 동안 전쟁을 했는데 전쟁은 얼마나 오래 걸렸죠?"
        },
        {
          "character": "물짱구",
          "line": "그야...음 난 잘 모르겠는데 알 것두 같고 모를 것두 같고..."
        },
        {
          "character": "일동",
          "line": "30년!"
        },
        {
          "character": "역사",
          "line": "자!어서 답하시요.당신은 이 답을 분명히..."
        },
        {
          "character": "물짱구",
          "line": "교장!난 이 시험을 못 치루겠소.이 친구들은 내게 컨닝을 시키려 하고 있소."
        },
        {
          "character": "교장",
          "line": "저리들 가서 앉으셔요."
        },
        {
          "character": "물짱구",
          "line": "30년 전쟁이 얼마나 길게 걸렸느냐고요?"
        },
        {
          "character": "역사",
          "line": "그렇소!"
        },
        {
          "character": "물짱구",
          "line": "그것은 내가 알지 그건 정확히 7미터요.암 7미터지 자 어서 수업료나 돌려 주시요."
        },
        {
          "character": "역사",
          "line": "맞았소.옳은 대답이요.(객석을 향해) 우선 맞았다고 해둬야지!"
        },
        {
          "character": "물짱구",
          "line": "뭐라고?그 답이 맞았다고!아니, 역사선생!"
        },
        {
          "character": "역사",
          "line": "어쨌든 그 답은 맞았소.마참 그의 사고진행이 단순히 피상적이 아니라는 것을 알려 줌과 동시에 마참!그는 이 문제를 현대 연구 방식에 따라 해결하려 하고 있소.마참!현대연구 방식은 어디에 기초를 두었느냐 하면 마참!에 또 그러니까----"
        },
        {
          "character": "물리",
          "line": "물론 상대성이지!질량의 법칙 즉 아이슈타인이지.네!아주 간단합니다.에- 또- 또---"
        },
        {
          "character": "수학",
          "line": "아!이젠 알았습니다.아인슈타인에 의하면 시간은 공간이나 물질과 마찬가지로 실제적이죠.질량계를 단위로 환원하고 회수를 미터로 나타낼 수 있는 겁니다.즉 7미터는 7년으로 30년 전쟁은 단지 7년을 끌었다라고 말할 수 있는데 왜냐하면 그것은 에-그 이유는 호 휴 에----"
        },
        {
          "character": "역사",
          "line": "그렇죠.그것은 마참!실제 전쟁은 대개 반나절씩 걸렸죠.마참!말하자면 스물 네시간 중 12시간을 싸웠다고 말할 수 있는데 30년은 결국 15년이 되는 셈이죠.그러나 그 15년두 다 싸움에 쓰였느냐 하면 병사들은 매일 식사하느라고 몇 시간씩 소비했을 거고 이 줄어든 시간 중에 전투 없는 견제 공세 낮잠 자는 시간 또는 잡담하는 시간 대 소변 하는 시간 전쟁 같지 않은 시간 등등에..."
        },
        {
          "character": "수학",
          "line": "주위 산만을 제하고 나면 이 수험생이 마친 아인슈타인에 등 가량으로 표시된 7미터의 시간이 남게 된 시간이죠."
        },
        {
          "character": "역사",
          "line": "그렇소!그의 답변은 맞았소.그러니까 이건 내 개인이 생각이지마는 마참!그에게 역사학 최우수를 인정하는 바요."
        },
        {
          "character": "일동",
          "line": "옳소!최우수요."
        },
        {
          "character": "교장",
          "line": "역사 최우수!"
        },
        {
          "character": "물짱구",
          "line": "이런 엉터리들 같으니!교장 이의가 있소."
        },
        {
          "character": "교장",
          "line": "이의는 기각!다음 물리선생."
        },
        {
          "character": "물짱구",
          "line": "난 이런 엉터리 시험 못 치루겠소."
        },
        {
          "character": "일동",
          "line": "안녕히 가십시오."
        },
        {
          "character": "물짱구",
          "line": "어...천만에!아 네놈들이 날 화나게 해서 스스로 날 가도록 할 작정이었구나!안되지.어디 잘 들 해 보시지.이 사기꾼들아!"
        },
        {
          "character": "물리",
          "line": "자, 앉으시지!"
        },
        {
          "character": "물짱구",
          "line": "좋다.아, 당신은 우리가 늘 뭐라고 불렀는지 아시요.바로 식인종이라고 불렀소.당신은 늘 지금처럼 입안에 손가락을 넣고 다녔으니까 식인종씨 어서 어려운 질문이나 해서 날 낙제시키시지!"
        },
        {
          "character": "물리",
          "line": "아, 그럽시다!그럼 질문이오!우리가 교외의 시계탑으로부터 점점 멀어질 때 그 시계탑은 점점 작아져 보이는데 그건 정말 작아지는 걸까요?아니면 시력에 착각 때문에 작아져 보이는 걸까요?"
        },
        {
          "character": "물짱구",
          "line": "내가 알 턱이 있나 난 멀리 갈수록 점점 더 커져 보이는데!"
        },
        {
          "character": "일동",
          "line": "네?"
        },
        {
          "character": "물리",
          "line": "에 또 한 마디로 말해서 당신의 답은..."
        },
        {
          "character": "물짱구",
          "line": "에 또 한 마디로 말해서 당신의 답은...에라이 당나귀야!또 뭐라고 주절대서 맞았다고 하려고...내 대답은 당나귀요.어쩌겠소?"
        },
        {
          "character": "물리",
          "line": "이 천하에 못된..."
        },
        {
          "character": "교장",
          "line": "물리선생 고정하시요.그는..."
        },
        {
          "character": "물리",
          "line": "그의 대답은 맞았소."
        },
        {
          "character": "물짱구",
          "line": "아니 뭐라고요?하!이런 세상에!"
        },
        {
          "character": "물리",
          "line": "매우 어려운 답변이지만 가장 훌륭한 해답이었소.그것은 에또--- 에또---"
        },
        {
          "character": "물짱구",
          "line": "에또--- 에또--- 뭐가 생각나나?이 바보 같은 얼간이 식인종 당나귀선생아!"
        },
        {
          "character": "물리",
          "line": "그렇지!당나귀는 슬프게 보입니다.왜 슬프게 보이느냐하면 그것은 우리가 모두 착각에 희생자이기 때문입니다.그러면 어떤 착각이 당나귀의 감각에 영향을 미칠까...에또--- 대개는 시력에 착각이지만 당나귀 역시 어떤 물체에서 멀어질수록 적게 보입니다.이 응시자는 우리에게 감각이 기만적인 경우 슬픈 표정을 갖게 한다는 사실까지도 우리에게 일깨워 줬습니다.에또--- 문제는 시계였지만 결국 작게 보이는 것은 시력에 착각 때문이라는 답변을 내 놓은 것입니다.그의 답변은 맞았습니다.나는 그에게 물리 최우수를 주겠소!"
        },
        {
          "character": "교장",
          "line": "물리 최우수!"
        },
        {
          "character": "일동",
          "line": "브라보!"
        },
        {
          "character": "물짱구",
          "line": "이의가 있소!"
        },
        {
          "character": "교장",
          "line": "기각!다음 지리선생 수고하시지요."
        },
        {
          "character": "물짱구",
          "line": "도대체 이게 어떻게 된 거요?교장선생님, 약속할게 있소.단 한과목이라도 낙제하면 그땐 수업료를 돌려주어야 하오!"
        },
        {
          "character": "교장",
          "line": "좋소!"
        },
        {
          "character": "물짱구",
          "line": "좋다!이제는 안 넘어 간다.자!"
        },
        {
          "character": "교장",
          "line": "지리 선생.지리 선생.수고 하시요."
        },
        {
          "character": "지리",
          "line": "잘 생각해서 답하시요.미국에 초대 대통령인 죠지 워싱턴을 기념하여 유명한 미국의 수도이름은?"
        },
        {
          "character": "물짱구",
          "line": "그야 모스크바지!"
        },
        {
          "character": "일동",
          "line": "예?"
        },
        {
          "character": "물짱구",
          "line": "이번에야 맞았다고 돌려 대지 못하겠지.나도 꽤 영리하단 말이야."
        },
        {
          "character": "지리",
          "line": "나도 그렇게 대답하리라 생각하오.그건 맞은 답이요."
        },
        {
          "character": "물짱구",
          "line": "지리 선생 당신 혹시 돈 것 아니요."
        },
        {
          "character": "지리",
          "line": "아주 훌륭하오.감탄했소.이 수험생은 세계정세에 매우 민감합니다.현대에 세계정세에 민주주의와 공산주의로써 두 주류로서 나누어졌다고 할 수 있겠는데 민주주의 하면 미국에 워싱턴을 생각하게 되고 공산주의 하면 소련에 모스크바라고 대답함으로써 워싱턴을 연상하게 할 대칭적인 답변을 한 것입니다.그는 지리학이나 역사학은 물론 상식문제까지도 넓은 안목을 가지고 있음이 입증되었습니다.난 이 수험생에게 지리학 최우수의 학점을 이 수험생에게 주고 싶습니다."
        },
        {
          "character": "교장",
          "line": "지리학 최우수!"
        },
        {
          "character": "일동",
          "line": "최우수 이의 없음!"
        },
        {
          "character": "교장",
          "line": "자!이제까지의 모든 시험에 합격했소.나머지 수학만 합격하면 그는 이 졸업장에 쓰인 데로 모든 것을 다 배운 우수한 자임이 증명되는 거요.자!그럼 수학선생."
        },
        {
          "character": "물짱구",
          "line": "야!정말 대단한 천재들만 모였구나.정치가가 되였으면 부정으로 치부하고도 남아서 거스름까지 받겠다.그러나 아직 희망은 있어.난 원래 수학과는 담을 쌓은 처지니까!2 x 2 = 3.사과 8개에다 3개의 배를 합하면 27개의 살구가 되지.이게 내 특유의 계산법이거든.어때!이래도 맞았다고 하겠소.하하하---하나만 틀리면 돼.하나만!"
        },
        {
          "character": "수학",
          "line": "당신은 이 시험을 농으로 생각해선 안 되요.난 두 문제를 드리겠소.하나는 쉽고 하나는 어렵고요."
        },
        {
          "character": "물짱구",
          "line": "하나는 쉽고 하나는 어렵소?에라이, 못난 참새 선생아!집에 가서 앞치마나 차고 있으시지!난 칠판에 그렸던 그 당신의 그 여우같은 꼬락서니를 똑똑히 기억하고 있지!"
        },
        {
          "character": "수학",
          "line": "이번에 미술 시험이라면 최우수를 주겠지만..."
        },
        {
          "character": "물짱구",
          "line": "최우수?아니요!아니요!"
        },
        {
          "character": "수학",
          "line": "그럼 쉬운 문제 빛에 속도를 x.태양과 시리우스 성자와의 거리를 y로 표시할 때---------에 체적은?얼마나 되지?"
        },
        {
          "character": "일동",
          "line": "아니?수학선생!"
        },
        {
          "character": "교장",
          "line": "수학선생.정신 있소?"
        },
        {
          "character": "물짱구",
          "line": "가만있자...."
        },
        {
          "character": "역사",
          "line": "아니?어쩌자고 수학선생 이러시오?"
        },
        {
          "character": "일동",
          "line": "아니, 수학선생!"
        },
        {
          "character": "물짱구",
          "line": "좀 조용히 하시지!여긴 시험장이야.그리고 수학선생 다시 한번 너무 빨리 하는 통에 문제를 잘 못 들었는데 문제가 너무 복잡해서..."
        },
        {
          "character": "수학",
          "line": "천만에 니 따위가 들었건 안 들었건 내 알 바 아니야!"
        },
        {
          "character": "교장",
          "line": "아이구!녹았구나."
        },
        {
          "character": "수학",
          "line": "자!빨리 해 보시요."
        },
        {
          "character": "물짱구",
          "line": "모르겠소.이건 정말 모르겠는데..."
        },
        {
          "character": "수학",
          "line": "그럼 낙제요!교장선생님!난 수학시험을 낙제로 주장합니다."
        },
        {
          "character": "물짱구",
          "line": "뭐?낙제!오...그렇구나!오...내 수업료!내 수업료를 돌려 주시요."
        },
        {
          "character": "교장",
          "line": "아니?이게 고작 수학선생이 하는 짓이요."
        },
        {
          "character": "일동",
          "line": "헛수고했구나!빌어먹을----"
        },
        {
          "character": "수학",
          "line": "미안합니다.여러분 그러나 이미 낙제한 이상 그의 요구는 정당합니다.그는 수험료를 도로 찾아갈 권리가 있습니다."
        },
        {
          "character": "물짱구",
          "line": "그렇구 말고요.수학선생은 똑똑해서 내 한턱내지 술을 못 마신다면 스타킹이라도 하나 선사하겠습니다.오.내 수험료!"
        },
        {
          "character": "교장",
          "line": "수학선생은 당장 파면이요!"
        },
        {
          "character": "수학",
          "line": "할 수 없습니다.그러나 여긴 훌륭한 학교입니다.학생을 교육하는 것입니다.만일 수험료를 내고 공부했는데 아무 것도 배운 것이 없다면 마땅히 돈을 도루 돌려줘야지요.그것이 학교의 명예를 지키는 것이 아니겠습니까?그런데 물짱구 수험료를 전부 얼마나 되죠?"
        },
        {
          "character": "물짱구",
          "line": "내 정확히 말씀드리죠.난 전부 4년간 다녔습니다 처음 2년간은 한 학기에 15000원 씩 4학기니까 6만원, 다음 2년 간은 1학기 20000원 씩 4학기니까 8만원.합해서 14만원 게다가 4년 간의 책값이 무려 육만 구천 삼백 원!게다가 잡부금 실습비 기타 합해서 12만 3천 7백 12원.모두 합해서 33만 3천 12원인데 12원은 학교에 기부하죠.나머지 33만 3 천원만 돌려주십시오!"
        },
        {
          "character": "수학",
          "line": "맞았소!"
        },
        {
          "character": "물짱구",
          "line": "틀림없지요.암!이건 정말 틀림없습니다.믿어도 좋소.오!내 수험료..."
        },
        {
          "character": "수학",
          "line": "정말 정확하고 적은 단위까지 훌륭합니다.축하합니다."
        },
        {
          "character": "물짱구",
          "line": "원 천만예요.다 수학선생님이 도와주신 덕이죠."
        },
        {
          "character": "수학",
          "line": "이것이 나의 둘째 문제였소."
        },
        {
          "character": "물짱구",
          "line": "뭐라고요?"
        },
        {
          "character": "수학",
          "line": "난 이 친구가 수학시험에 합격했음을 보장합니다.지금 여러분이 보신 바와 같이 가장 담을 쌓고 있는 수학과목에 가장 적은 단위까지 훌륭히 계산해 냈습니다.물짱구씨는 수학에 천재입니다.천재!"
        },
        {
          "character": "일동",
          "line": "아까는 실례했소."
        },
        {
          "character": "교장",
          "line": "내일부터는 교무주임이요!"
        },
        {
          "character": "수학",
          "line": "감사합니다."
        },
        {
          "character": "교장",
          "line": "모든 시험 경과 발표를 하겠습니다.물짱구씨는 모든 시험에 최우수에 최우수 그리고 천재적으로 돌파했습니다.물짱구씨!당신을 이토록 훌륭히 가르친 우리에게 축하를 드리는 바입니다.내가 집어던지기 전에 썩 꺼져버려!이봐!"
        },
        {
          "character": "역사",
          "line": "나한테도 당해 봐라!"
        },
        {
          "character": "물리",
          "line": "내가 당나귀 식인종?"
        },
        {
          "character": "지리",
          "line": "다리몽둥이를 뿐질러줄까?"
        },
        {
          "character": "수학",
          "line": "참새 요놈!"
        },
        {
          "character": "사환",
          "pre_directions": "(들어온다)",
          "line": "부르셨습니까?"
        },
        {
          "character": "교장",
          "line": "이 물건을 치워버려"
        },
        {
          "character": "사환",
          "line": "네!"
        },
        {
          "character": "교장",
          "line": "애 여러분 여러분에 눈부신 협조에 감사를 드리는 바이옵니다.먼 훗날 이 학교에 출신들은 이렇게 시험에 실패하지 않는다는 것을 커다란 자랑거리로 삼고 싶으며 다시 한번 여러분에게 감사를 드리는 바이옵니다.하하 하하------"
        }
      ],
      "directions_end": [
        {
          "type": "direction",
          "content": "(막 내린다)"
        }
      ]
    }
  ]
}